Metadata-Version: 2.1
Name: comlipy
Version: 1.2.1
Summary: comlipy by slashplus - lint commit messages with python
Home-page: https://gitlab.com/slashplus-build/comlipy/
License: MIT
Keywords: linting, git, git-hooks, commit-msg
Author: slashplus
Author-email: info@slashplus.de
Maintainer: slashplus
Maintainer-email: info@slashplus.de
Requires-Python: >=3.7
Classifier: Environment :: Console
Classifier: Intended Audience :: Developers
Classifier: Intended Audience :: System Administrators
Classifier: License :: OSI Approved :: MIT License
Classifier: Operating System :: MacOS :: MacOS X
Classifier: Operating System :: POSIX
Classifier: Operating System :: POSIX :: Linux
Classifier: Operating System :: Unix
Classifier: Programming Language :: Python
Classifier: Programming Language :: Python :: 3
Classifier: Programming Language :: Python :: 3 :: Only
Classifier: Programming Language :: Python :: 3.7
Classifier: Programming Language :: Python :: 3.8
Classifier: Topic :: Software Development
Classifier: Topic :: Software Development :: Build Tools
Classifier: Topic :: System :: Systems Administration
Requires-Dist: click (==7.0)
Requires-Dist: pyyaml (==5.3)
Project-URL: Documentation, https://gitlab.com/slashplus-build/comlipy/tree/master/docs
Project-URL: Repository, https://gitlab.com/slashplus-build/comlipy/
